maximo_gui_connector/__init__.py
maximo_gui_connector/__version__.py
maximo_gui_connector/constants.py
maximo_gui_connector/main.py
maximo_gui_connector/maximo_gui_connector.py
maximo_gui_connector/utilities.py
maximo_gui_connector-0.7.10.dist-info/LICENSE
maximo_gui_connector-0.7.10.dist-info/METADATA
maximo_gui_connector-0.7.10.dist-info/WHEEL
maximo_gui_connector-0.7.10.dist-info/top_level.txt
maximo_gui_connector-0.7.10.dist-info/RECORD
