Metadata-Version: 2.1
Name: maximo-gui-connector
Version: 0.7.10
Summary: Small Library that makes it easier to create scripts to automate IBM Maximo's frontend
Home-page: https://github.com/LukeSavefrogs/maximo-gui-connector
Author: Luca Salvarani
Author-email: lucasalvarani99@gmail.com
License: MIT
Platform: UNKNOWN
Classifier: License :: OSI Approved :: MIT License
Classifier: Programming Language :: Python
Classifier: Programming Language :: Python :: 3
Classifier: Programming Language :: Python :: 3.6
Classifier: Programming Language :: Python :: Implementation :: CPython
Classifier: Programming Language :: Python :: Implementation :: PyPy
Requires-Python: >=3.0
Requires-Dist: selenium
Requires-Dist: webdriver-manager
Provides-Extra: webdriver_auto-update
Requires-Dist: webdriver-manager ; extra == 'webdriver_auto-update'
